pluggableapp
