Metadata-Version: 1.1
Name: django-pluggable-apps
Version: 1.1
Summary: A pluggable system for django applications
Home-page: http://packages.python.org/DjangoPluggableApp/
Author: Gael Pasgrimaud
Author-email: gpasgrimaud@bearstech.com
License: BSD
Keywords: django plugin apps
Platform: UNKNOWN
Classifier: Framework :: Django
Classifier: Intended Audience :: Developers
Classifier: License :: OSI Approved :: BSD License
Classifier: Operating System :: POSIX
